{
  "1": {
    "serverName": "Augury Rock",
    "idWorld": 2103,
    "date": "07/10/2022",
    "time": "21:57:21",
    "worldColor": "red",
    "nbKills": 992,
    "nbDeaths": 922,
    "ratio": 1.0759219088937093,
    "skirmishKills": 0,
    "skirmishDeaths": 0,
    "skirmishRatio": 0,
    "Center": {
      "nbKills": 412,
      "nbDeaths": 238,
      "ratio": 1.731,
      "skirmishKills": 0,
      "skirmishDeaths": 0,
      "skirmishRatio": 0
    },
    "RedHome": {
      "nbKills": 36,
      "nbDeaths": 92,
      "ratio": 0.391,
      "skirmishKills": 0,
      "skirmishDeaths": 0,
      "skirmishRatio": 0
    },
    "BlueHome": {
      "nbKills": 162,
      "nbDeaths": 352,
      "ratio": 0.46,
      "skirmishKills": 0,
      "skirmishDeaths": 0,
      "skirmishRatio": 0
    },
    "GreenHome": {
      "nbKills": 382,
      "nbDeaths": 240,
      "ratio": 1.592,
      "skirmishKills": 0,
      "skirmishDeaths": 0,
      "skirmishRatio": 0
    },
    "skirmishScore": {
      "1": "green",
      "2": "red",
      "3": "blue"
    }
  },
  "2": {
    "serverName": "Augury Rock",
    "idWorld": 2103,
    "date": "07/10/2022",
    "time": "23:57:23",
    "worldColor": "red",
    "nbKills": 3211,
    "nbDeaths": 3302,
    "ratio": 0.9724409448818898,
    "skirmishKills": 2219,
    "skirmishDeaths": 2380,
    "skirmishRatio": 0.9323529411764706,
    "Center": {
      "nbKills": 1288,
      "nbDeaths": 1024,
      "ratio": 1.258,
      "skirmishKills": 876,
      "skirmishDeaths": 786,
      "skirmishRatio": 1.1145038167938932
    },
    "RedHome": {
      "nbKills": 228,
      "nbDeaths": 338,
      "ratio": 0.675,
      "skirmishKills": 192,
      "skirmishDeaths": 246,
      "skirmishRatio": 0.7804878048780488
    },
    "BlueHome": {
      "nbKills": 715,
      "nbDeaths": 783,
      "ratio": 0.913,
      "skirmishKills": 553,
      "skirmishDeaths": 431,
      "skirmishRatio": 1.283062645011601
    },
    "GreenHome": {
      "nbKills": 980,
      "nbDeaths": 1157,
      "ratio": 0.847,
      "skirmishKills": 598,
      "skirmishDeaths": 917,
      "skirmishRatio": 0.6521264994547438
    },
    "skirmishScore": {
      "1": "green",
      "2": "blue",
      "3": "red"
    }
  },
  "3": {
    "serverName": "Augury Rock",
    "idWorld": 2103,
    "date": "08/10/2022",
    "time": "02:34:46",
    "worldColor": "red",
    "nbKills": 3658,
    "nbDeaths": 3759,
    "ratio": 0.9731311519021016,
    "skirmishKills": 447,
    "skirmishDeaths": 457,
    "skirmishRatio": 0.9781181619256017,
    "Center": {
      "nbKills": 1496,
      "nbDeaths": 1258,
      "ratio": 1.189,
      "skirmishKills": 208,
      "skirmishDeaths": 234,
      "skirmishRatio": 0.8888888888888888
    },
    "RedHome": {
      "nbKills": 382,
      "nbDeaths": 438,
      "ratio": 0.872,
      "skirmishKills": 154,
      "skirmishDeaths": 100,
      "skirmishRatio": 1.54
    },
    "BlueHome": {
      "nbKills": 758,
      "nbDeaths": 841,
      "ratio": 0.901,
      "skirmishKills": 43,
      "skirmishDeaths": 58,
      "skirmishRatio": 0.7413793103448276
    },
    "GreenHome": {
      "nbKills": 1022,
      "nbDeaths": 1222,
      "ratio": 0.836,
      "skirmishKills": 42,
      "skirmishDeaths": 65,
      "skirmishRatio": 0.6461538461538462
    },
    "skirmishScore": {
      "1": "green",
      "2": "blue",
      "3": "red"
    }
  },
  "4": {
    "serverName": "Augury Rock",
    "idWorld": 2103,
    "date": "08/10/2022",
    "time": "05:22:52",
    "worldColor": "red",
    "nbKills": 3668,
    "nbDeaths": 3807,
    "ratio": 0.9634883110060415,
    "skirmishKills": 10,
    "skirmishDeaths": 48,
    "skirmishRatio": 0.20833333333333334,
    "Center": {
      "nbKills": 1500,
      "nbDeaths": 1277,
      "ratio": 1.175,
      "skirmishKills": 4,
      "skirmishDeaths": 19,
      "skirmishRatio": 0.21052631578947367
    },
    "RedHome": {
      "nbKills": 383,
      "nbDeaths": 453,
      "ratio": 0.845,
      "skirmishKills": 1,
      "skirmishDeaths": 15,
      "skirmishRatio": 0.06666666666666667
    },
    "BlueHome": {
      "nbKills": 761,
      "nbDeaths": 845,
      "ratio": 0.901,
      "skirmishKills": 3,
      "skirmishDeaths": 4,
      "skirmishRatio": 0.75
    },
    "GreenHome": {
      "nbKills": 1024,
      "nbDeaths": 1232,
      "ratio": 0.831,
      "skirmishKills": 2,
      "skirmishDeaths": 10,
      "skirmishRatio": 0.2
    },
    "skirmishScore": {
      "1": "green",
      "2": "red",
      "3": "blue"
    }
  }
}